hlda/__init__.py
hlda/sampler.py
hlda-0.3.1.dist-info/LICENSE.txt
hlda-0.3.1.dist-info/METADATA
hlda-0.3.1.dist-info/WHEEL
hlda-0.3.1.dist-info/top_level.txt
hlda-0.3.1.dist-info/RECORD
