Metadata-Version: 2.1
Name: hlda
Version: 0.3.1
Summary: Gibbs sampler for the Hierarchical Latent Dirichlet Allocation topic model. This is based on the hLDA implementation from Mallet, having a fixed depth on the nCRP tree.
Home-page: https://github.com/joewandy/hlda
Author: Joe Wandy
Author-email: joe.wandy@glasgow.ac.uk
License: UNKNOWN
Platform: UNKNOWN
Classifier: Programming Language :: Python :: 3
Classifier: License :: OSI Approved :: GNU General Public License v3 (GPLv3)
Classifier: Operating System :: OS Independent
Requires-Python: >=3
Requires-Dist: numpy
